prysa/__init__.py
prysa/cli/__init__.py
prysa/cli/commands/__init__.py
prysa/cli/commands/add.py
prysa/cli/commands/list_tools.py
prysa/cli/commands/new.py
prysa/cli/commands/remove.py
prysa/cli/commands/show_config.py
prysa/cli/main.py
prysa/config/__init__.py
prysa/config/config_manager.py
prysa/core/__init__.py
prysa/core/abstractions.py
prysa/core/plugins.py
prysa/main.py
prysa/scaffolder/__init__.py
prysa/tools/__init__.py
prysa/tools/linters/__init__.py
prysa/tools/managers/__init__.py
prysa/tools/testers/__init__.py
prysa/utils/__init__.py
prysa-0.1.2.dist-info/METADATA
prysa-0.1.2.dist-info/WHEEL
prysa-0.1.2.dist-info/entry_points.txt
prysa-0.1.2.dist-info/RECORD
