Metadata-Version: 2.3
Name: prysa
Version: 0.1.2
Summary: A modern Python CLI tool to scaffold and configure new Python library projects with best practices.
License: MIT
Keywords: python,cli,scaffold,project,library,automation
Author: Eduardo Alapisco
Author-email: alapisco@gmail.com
Requires-Python: >=3.8,<4.0
Classifier: Intended Audience :: Developers
Classifier: License :: OSI Approved :: MIT License
Classifier: Operating System :: OS Independent
Classifier: Programming Language :: Python :: 3
Classifier: Programming Language :: Python :: 3.8
Classifier: Programming Language :: Python :: 3.9
Classifier: Programming Language :: Python :: 3.10
Classifier: Programming Language :: Python :: 3.11
Classifier: Programming Language :: Python :: 3.12
Classifier: Programming Language :: Python :: 3.13
Classifier: Topic :: Software Development :: Build Tools
Classifier: Topic :: Software Development :: Libraries :: Python Modules
Requires-Dist: typer (>=0.12.3,<0.13.0)
Project-URL: Homepage, https://github.com/alapisco/prysa
Project-URL: Repository, https://github.com/alapisco/prysa
